setup.py
EAC/__init__.py
EAC.egg-info/PKG-INFO
EAC.egg-info/SOURCES.txt
EAC.egg-info/dependency_links.txt
EAC.egg-info/top_level.txt