Metadata-Version: 1.1
Name: EAC
Version: 0.1
Summary: Enhanced Autocorrelation
Home-page: http://yeisoncardona.com/
Author: Yeison Cardona
Author-email: yeisoneng@gmail.com
License: BSD License
Download-URL: https://bitbucket.org/yeisoneng/python-eac/downloads
Platform: UNKNOWN
